AUTHOR.txt
CHANGES.txt
LICENSE.txt
README.txt
TODOS.txt
bootstrap.py
buildout.cfg
setup.py
src/zope/__init__.py
src/zope.dependencytool.egg-info/PKG-INFO
src/zope.dependencytool.egg-info/SOURCES.txt
src/zope.dependencytool.egg-info/dependency_links.txt
src/zope.dependencytool.egg-info/entry_points.txt
src/zope.dependencytool.egg-info/namespace_packages.txt
src/zope.dependencytool.egg-info/not-zip-safe
src/zope.dependencytool.egg-info/requires.txt
src/zope.dependencytool.egg-info/top_level.txt
src/zope/dependencytool/__init__.py
src/zope/dependencytool/dependency.py
src/zope/dependencytool/finddeps.py
src/zope/dependencytool/importfinder.py
src/zope/dependencytool/tests/__init__.py
src/zope/dependencytool/tests/sample.py
src/zope/dependencytool/tests/test_dependency.py
src/zope/dependencytool/tests/test_finddeps.py
src/zope/dependencytool/tests/test_importfinder.py
src/zope/dependencytool/tests/pkg/__init__.py
src/zope/dependencytool/tests/pkg/module.py
